Metadata-Version: 1.1
Name: DiscordOauth
Version: 1.0.0
Summary: DiscordOauth
Home-page: UNKNOWN
Author: MrStretch
Author-email: markustraus@gmail.com
License: MIT
Keywords: discord,oauth
Platform: UNKNOWN
Classifier: Development Status :: 5 - Production/Stable
Classifier: Intended Audience :: Education
Classifier: Operating System :: Microsoft :: Windows :: Windows 10
Classifier: License :: OSI Approved :: MIT License
Classifier: Programming Language :: Python :: 3
